myodev/__init__.py
myodev/features/__init__.py
myodev/features/simple.py
myodev/ml/__init__.py
myodev/processing/__init__.py
myodev/processing/load.py
myodev-0.0.4.dist-info/LICENCE
myodev-0.0.4.dist-info/METADATA
myodev-0.0.4.dist-info/WHEEL
myodev-0.0.4.dist-info/top_level.txt
myodev-0.0.4.dist-info/RECORD
